centrosome/radial_power_spectrum.py
centrosome/_fastemd.cpython-311-darwin.so
centrosome/princomp.py
centrosome/zernike.py
centrosome/index.py
centrosome/_cpmorphology2.cpython-311-darwin.so
centrosome/rankorder.py
centrosome/_propagate.cpython-311-darwin.so
centrosome/bg_compensate.py
centrosome/__init__.py
centrosome/cpmorphology.py
centrosome/threshold.py
centrosome/mode.py
centrosome/_filter.cpython-311-darwin.so
centrosome/watershed.py
centrosome/outline.py
centrosome/kirsch.py
centrosome/smooth.py
centrosome/_convex_hull.cpython-311-darwin.so
centrosome/filter.py
centrosome/haralick.py
centrosome/fastemd.py
centrosome/otsu.py
centrosome/neighmovetrack.py
centrosome/_np_compat.py
centrosome/_lapjv.cpython-311-darwin.so
centrosome/propagate.py
centrosome/lapjv.py
centrosome-1.3.3.dist-info/RECORD
centrosome-1.3.3.dist-info/WHEEL
centrosome-1.3.3.dist-info/top_level.txt
centrosome-1.3.3.dist-info/METADATA
centrosome-1.3.3.dist-info/licenses/LICENSE
