Metadata-Version: 2.4
Name: centrosome
Version: 1.3.3
Summary: An open source image processing library
Home-page: https://github.com/CellProfiler/centrosome
Author: Nodar Gogoberidze
Author-email: ngogober@broadinstitute.org
License: BSD
Classifier: Development Status :: 5 - Production/Stable
Classifier: Intended Audience :: Science/Research
Classifier: License :: OSI Approved :: BSD License
Classifier: Operating System :: OS Independent
Classifier: Programming Language :: C
Classifier: Programming Language :: C++
Classifier: Programming Language :: Cython
Classifier: Programming Language :: Python :: 3
Classifier: Programming Language :: Python :: 3.9
Classifier: Programming Language :: Python :: 3.10
Classifier: Programming Language :: Python :: 3.11
Classifier: Programming Language :: Python :: 3.12
Classifier: Programming Language :: Python :: 3.13
Classifier: Topic :: Scientific/Engineering :: Bio-Informatics
Classifier: Topic :: Scientific/Engineering
License-File: LICENSE
Requires-Dist: deprecation
Requires-Dist: numpy>=1.18.2
Requires-Dist: pillow<12,>=7.1.0
Requires-Dist: scikit-image<1,>=0.17.2
Requires-Dist: scipy!=1.11.0,<2,>=1.4.1
Provides-Extra: dev
Requires-Dist: black==19.10b0; extra == "dev"
Requires-Dist: pre-commit==1.20.0; extra == "dev"
Provides-Extra: test
Requires-Dist: pytest; extra == "test"
Dynamic: author
Dynamic: author-email
Dynamic: classifier
Dynamic: home-page
Dynamic: keywords
Dynamic: license
Dynamic: license-file
Dynamic: provides-extra
Dynamic: requires-dist
Dynamic: summary
